README.md
setup.py
edufin/__init__.py
edufin/finan.py
edufin.egg-info/PKG-INFO
edufin.egg-info/SOURCES.txt
edufin.egg-info/dependency_links.txt
edufin.egg-info/requires.txt
edufin.egg-info/top_level.txt