Metadata-Version: 2.1
Name: edufin
Version: 0.1
Summary: Una biblioteca educativa de finanzas
Home-page: https://github.com/msalaztor
Author: Mario Rene Salazar Torres
Author-email: mrsalazar@outlook.com
License: UNKNOWN
Platform: UNKNOWN
Classifier: License :: OSI Approved :: MIT License
Classifier: Programming Language :: Python :: 3
Classifier: Programming Language :: Python :: 3.7
Classifier: Programming Language :: Python :: 3.8
Classifier: Programming Language :: Python :: 3.9
